nba_draft_predictor/__init__.py
nba_draft_predictor-0.1.0.dist-info/METADATA
nba_draft_predictor-0.1.0.dist-info/WHEEL
nba_draft_predictor-0.1.0.dist-info/top_level.txt
nba_draft_predictor-0.1.0.dist-info/RECORD
