Metadata-Version: 2.1
Name: nba-draft-predictor
Version: 0.1.0
Summary: NBA Draft Prediction Models and Utilities
Home-page: https://github.com/pranavsat/nba-draft-predictor
Author: Pranav Sathyababu
Author-email: pranavsathya56@gmail.com
Classifier: Programming Language :: Python :: 3
Classifier: Programming Language :: Python :: 3.11
Classifier: License :: OSI Approved :: MIT License
Classifier: Operating System :: OS Independent
Requires-Python: ==3.11.4
Requires-Dist: scikit-learn==1.5.1
Requires-Dist: pandas==2.2.2
Requires-Dist: joblib==1.4.2
Requires-Dist: xgboost==2.1.0
Requires-Dist: hyperopt==0.2.7
Requires-Dist: lightgbm==4.4.0
Requires-Dist: lime==0.2.0.1
Requires-Dist: wandb==0.17.4
